AERzip/CompressedFileHeader.py
AERzip/__init__.py
AERzip/functions.py
aerzip-1.0.1.dist-info/METADATA
aerzip-1.0.1.dist-info/WHEEL
aerzip-1.0.1.dist-info/licenses/LICENSE
aerzip-1.0.1.dist-info/RECORD
