Metadata-Version: 2.4
Name: AERzip
Version: 1.0.1
Summary: Useful tools to compress and decompress AEDAT files in Python
Project-URL: Repository, https://github.com/alvayus/AERzip
Author-email: Álvaro Ayuso Martínez <aayuso@us.es>
License:                     GNU GENERAL PUBLIC LICENSE
License-File: LICENSE
Requires-Dist: pynavis
